STIM_Module/API_KEY.py
STIM_Module/__init__.py
STIM_Module/__main__.py
STIM_Module/analysis.py
STIM_Module/api_funcs.py
STIM_Module/application.py
STIM_Module/dummy_matplot.py
STIM_Module/font.py
STIM_Module/new_exceptions.py
STIM_Module/paramPassback.py
STIM_Module/assets/Images/lol_image.jpg
STIM_Module-1.0.0.dist-info/LICENSE.txt
STIM_Module-1.0.0.dist-info/METADATA
STIM_Module-1.0.0.dist-info/WHEEL
STIM_Module-1.0.0.dist-info/entry_points.txt
STIM_Module-1.0.0.dist-info/top_level.txt
STIM_Module-1.0.0.dist-info/RECORD
