Metadata-Version: 2.1
Name: STIM-Module
Version: 1.0.0
Summary: League of Legends STIM Module
Author-email: Jaxton 'Jax' Willman <jaxtonwillman@ufl.edu>, Benjamin 'Ben' Covert <benjamin.covert@ufl.edu>, David 'Sandy' Hutchins <davidhutchins@ufl.edu>
License: MIT License        
Project-URL: Homepage, https://jaxjaxw.github.io/STIM_Module/index.html
Project-URL: Issues, https://github.com/ben-covert2020/STIM_Module/issues
Project-URL: Documentation, https://jaxjaxw.github.io/STIM_Module/documentation/index.html
Project-URL: Source Code, https://github.com/ben-covert2020/STIM_Module
Project-URL: Funding, https://www.patreon.com/jaxjaxw
Classifier: Programming Language :: Python :: 3
Classifier: License :: OSI Approved :: MIT License
Classifier: Operating System :: OS Independent
Classifier: Development Status :: 3 - Alpha
Requires-Python: >=3.7
License-File: LICENSE.txt
Requires-Dist: sphinx
Requires-Dist: matplotlib
Requires-Dist: tk
Requires-Dist: pandas
Requires-Dist: numpy
Requires-Dist: requests
Requires-Dist: datetime
Requires-Dist: twisted
Provides-Extra: dev
Requires-Dist: build ; extra == 'dev'
Requires-Dist: bumpver ; extra == 'dev'
Requires-Dist: twine ; extra == 'dev'
Requires-Dist: pip-tools ; extra == 'dev'
Requires-Dist: pytest ; extra == 'dev'
